[
  {
    "id": 1,
    "question": "1. 国家秘密是指关系国家的安全和利益，依照法定程序确定，在一定时间内只限一定范围的人员知悉的事项。（  ）"
  },
  {
    "id": 2,
    "question": "2. 一切国家机关、武装力量、政党、社会团体、企业事业单位和公民都有保守国家秘密的义务。         （  ）"
  },
  {
    "id": 3,
    "question": "3. 单位可以把知悉国家秘密作为一种行政级别待遇，按照行政级别确定国家秘密知悉范围。          （  ）"
  },
  {
    "id": 4,
    "question": "4. 国家秘密知悉范围内的机关、单位、其有关工作人员不在知悉范围内，但因工作需要知悉国家秘密的，应当经单位负责人批准。（  ）"
  },
  {
    "id": 5,
    "question": "5.国家秘密知悉范围之外的人员，因工作需要知悉国家秘密的，应当经单位负责人同意。           （  ）"
  },
  {
    "id": 6,
    "question": "6. 单位负责人为本单位的定密负责人，对定密工作负总者。（  ）"
  },
  {
    "id": 7,
    "question": "7. 单位对所产生的国家秘密事项，应当按照保密事项范围的规定确定密级，同时确定保密期限和知悉范围。     （  ）"
  },
  {
    "id": 8,
    "question": "8. 国家秘密变更后，原定密机关、单位应及时在原国家秘密标志附近重新做出国家秘密标志，并书面通知知悉范围内的机关、单位和人员。                （  ）"
  },
  {
    "id": 9,
    "question": "9. 单位对已定密事项是否属于国家秘密或者属于何种密级有不同意见的，不得向原定密机关、单位提出异议。（×） 10. 涉密岗位是指在日常工作中产生、经管或者经常接触、知悉国家秘密事项的岗位。            （  ）"
  },
  {
    "id": 10,
    "question": "11. 涉密人员在非涉密出版物上发表文章、著作，不得涉及国家秘密。                （  ）"
  },
  {
    "id": 11,
    "question": "12. 涉密人员禁止向境外期刊等新闻出版机构投寄稿件。 （  ）"
  },
  {
    "id": 12,
    "question": "13. 涉密人员发表文章、著作凡涉及本单位、本系统业务工作的，应当事先经本单位或上级机关、单位保密审查、审批。  （  ）"
  },
  {
    "id": 13,
    "question": "14. 涉密载体是指以文字、数据、符号、图形、图像、声音等方式记载国家秘密信息的纸介质、光介质、电磁介质等各类物品。（  ）"
  },
  {
    "id": 14,
    "question": "15. 制作涉密载体应当在符合保密要求的场所进行。  （  ）"
  },
  {
    "id": 15,
    "question": "16. 涉密载体复制件应当加盖复制机关、单位戳记，并视同原件管理。                （  ）"
  },
  {
    "id": 16,
    "question": "17. 绝密级涉密载体一般不得复制、摘录、引用、汇编，确有工作需要的，必须征得原定密机关、单位或者其上级机关、单位同意。                   （  ）"
  },
  {
    "id": 17,
    "question": "18. 涉密载体可以通过普通邮政、快递等渠道传递。  （  ）"
  },
  {
    "id": 18,
    "question": "19. 对涉密科研项目文件资料，包括过程文件、电子文档等涉密载体，要进行全面清理、完整归档，个人应根据工作需耍自行妥善保管或者销段。              （  ）"
  },
  {
    "id": 19,
    "question": "20. 阅读和使用涉密载体应当在符合保密要求的办公场所进行。                  （  ）"
  },
  {
    "id": 20,
    "question": "21. 绝密级涉密载体应当在符合国家保密标准的设施、设备中保存，并指定专人管理。            （  ）"
  },
  {
    "id": 21,
    "question": "22. 机构撤并时，原机构的涉密载体移交给制发单位时，制发单位不收回的可自行处理。           （  ）"
  },
  {
    "id": 22,
    "question": "23. 保密要害部门、部位办公场所在采取必要的保密措施后。仍需要对进入的工勤人员严格监督管理。       （√） 24. 专用手机可以随意带入保密要害部门、部位。   （  ）"
  },
  {
    "id": 23,
    "question": "25.未经批准，不得将带有录音、录像、拍照、信息存储功能的设备带入保密要害部门、部位。         （  ）"
  },
  {
    "id": 24,
    "question": "26.涉密会议、活动应当按照“谁承办、谁负责”的原则进行管理。                 （  ）"
  },
  {
    "id": 25,
    "question": "27.重要涉密会议、重大涉密活动组织举办者应在必要时，请保密工作机构对保密工作进行监督和指导，并提供必要的安全保密技术服务保障。               （  ）"
  },
  {
    "id": 26,
    "question": "28.保密审查主要是对拟公开发布的信息是否涉及国家秘密进行审查，不需要对是否涉及工作秘密、商业秘密、个人隐私等进行甄别鉴定。                （  ）"
  },
  {
    "id": 27,
    "question": "29.在涉密科研项目结题阶段，要加强成果验收、奖项申报、专利申请等工作的保密管理。          （  ）"
  },
  {
    "id": 28,
    "question": "30.经严格审批，涉及敏感项目(如军工技术、军贸等)的驻外机构和企业可以雇佣外籍人员。          （  ）"
  },
  {
    "id": 29,
    "question": "31.任何组织和个人不得擅自对外提供国家秘密资料。 （  ）"
  },
  {
    "id": 30,
    "question": "32.党的纪律处分条例规定，泄露、扩散或者窃取党组织尚未公开事项或者其他应该保密的内容的，情节较重的，给予开除党籍处分。                  （  ）"
  },
  {
    "id": 31,
    "question": "33.“业务工作谁主管，保密工作谁负责”是保密工作的重要原则。                 （  ）"
  },
  {
    "id": 32,
    "question": "34.国家秘密的密级分为绝密、机密、秘密三级。   （  ）"
  },
  {
    "id": 33,
    "question": "35. 绝密级国家秘密是最重要的国家秘密，泄露会使国家安全和利益遭受特别严重的损害。          （  ）"
  },
  {
    "id": 34,
    "question": "36. 机密级国家秘密是重要的国家秘密，泄露会使国家安全和利益遭受严重的损害。            （  ）"
  },
  {
    "id": 35,
    "question": "37. 秘密级国家秘密是一般的国家秘密，泄露会使国家安全和利益遭受损害。              （  ）"
  },
  {
    "id": 36,
    "question": "38. 保守国家秘密是我国公民的一项基本义务。   （  ）"
  },
  {
    "id": 37,
    "question": "39. 涉密岗位根据涉及国家秘密的程度分为核心、重要和一般三个等级。                （  ）"
  },
  {
    "id": 38,
    "question": "40. 承担涉密项目研究、建设、管理任务的岗位应确定为重要涉密岗位。                （  ）"
  },
  {
    "id": 39,
    "question": "41. 核心涉密岗位是指年产生、处理6件(项)绝密级国家秘密事项的工作岗位。              （  ）"
  },
  {
    "id": 40,
    "question": "42. 国防科技工业涉密人员是指取得武器装备科研生产单位保密资格的企业事业单位中，在涉密岗位工作的人员。（  ）"
  },
  {
    "id": 41,
    "question": "43. 涉密人员应当具有中华人民共和国国籍。    （  ）"
  },
  {
    "id": 42,
    "question": "44. 涉密人员上岗前要经过保密审查，并接受保密教育培训。（  ）"
  },
  {
    "id": 43,
    "question": "45. 经审查合格，进入涉密岗位的人员须按照规定签订保密承诺书，明确享有的权利和应当承诺履行的保密义务。    （  ）"
  },
  {
    "id": 44,
    "question": "46. 单位应当定期对涉密人员进行复审，核心涉密人员每年复审一次，重要涉密人员每2年复审一次，一般涉密人员每3年复审一次。                 （  ）"
  },
  {
    "id": 45,
    "question": "47. 涉密人员在岗期间，保密工作机构应当会同人事部门，涉密人员所在部门有针对性地对其进行保密教育和检查、考核，对严重违反保密规定的应当及时调离涉密岗位。       （  ）"
  },
  {
    "id": 46,
    "question": "48. 一般涉密人员与境外人员通婚或者接受境外机构、组织及非亲属人员资助的，事后向单位报告即可。      （×） 49. 涉密人员本人或其直系亲属拟申请获得境外永久居留权、长期居留权或外国国籍的应当向单位报告。      （√） 50. 涉密人员离岗后，应当遵守脱密期限规定，核心涉密人员脱密期3年，重要涉密人员脱密期2年，一般涉密人员脱密期1年。                   （  ）"
  },
  {
    "id": 47,
    "question": "51. 涉密人员脱离涉密岗位3年内不得在境外驻华机构或者外商独资企业工作。              （  ）"
  },
  {
    "id": 48,
    "question": "52. 涉密人员脱密期内不得在境外驻华机构或者外商独资企业工作，但可以为境外组织或者人员提供劳务咨询或者其他服务。（  ）"
  },
  {
    "id": 49,
    "question": "53. 涉密人员脱密期内不得在国内中外合资企业工作。 （  ）"
  },
  {
    "id": 50,
    "question": "54. 涉密人员因私出境应经所在单位同意，还应按照有关规定办理保密审批手续。             （  ）"
  },
  {
    "id": 51,
    "question": "55. 涉密人员因公出国(境)的，应该按照行政隶属关系、干部(人事)管理权限和外事管理权限履行审批程序。     （√） 56. 涉密人员脱密期内未经批准可以因私出境。   （  ）"
  },
  {
    "id": 52,
    "question": "57. 涉密人员离开涉密岗位后，就不再对本人在原涉密岗位上知悉的国家秘密事项承担保密义务。        （  ）"
  },
  {
    "id": 53,
    "question": "58.涉密人员脱密期满后，对所知悉的国家秘密同样承担保密责任和义务。               （  ）"
  },
  {
    "id": 54,
    "question": "59. 出境后可能对国家安全造成危害或者对国家利益造成重大损失的涉密人员，不得批准出境。        （  ）"
  },
  {
    "id": 55,
    "question": "60. 涉密人员出国(境)期间受到境外机构、组织和人员的礼品馈赠不须向单位报告。            （  ）"
  },
  {
    "id": 56,
    "question": "61. 涉密单位应当对聘用的保安和临时工进行保密教育培训。                   （  ）"
  },
  {
    "id": 57,
    "question": "62. 在私人交往和通信中不得涉及或泄露国家秘密。  （  ）"
  },
  {
    "id": 58,
    "question": "63. 配偶、子女和本人都是涉密人员，互相谈论涉密事项没有关系。                 （  ）"
  },
  {
    "id": 59,
    "question": "64. 各级国家机关、单位对所产生的国家秘密事项，应当按照国家秘密及其密级具体范围的规定及时确定密级。    （  ）"
  },
  {
    "id": 60,
    "question": "65. 定密工作是指对机关、单位业务活动中所产生的国家秘密事项及时、准确确定其密级、保密期限、知悉范围，并对国家秘密载体做出标志，及时通知应当知悉的机关、单位和人员，并按照规定进行全过程管理的活动。            （  ）"
  },
  {
    "id": 61,
    "question": "66. 项目定密是指军工单位对从事的武器装备科研生产项目依法进行确定是否涉密以及是何种密级的工作。     （  ）"
  },
  {
    "id": 62,
    "question": "67. 国家秘密事项范围定得越宽，密级越高，越有利于国家秘密的安全。                （  ）"
  },
  {
    "id": 63,
    "question": "68. 国家秘密的标识为★，★前标密级，★后标保密期限。                             （  ）"
  },
  {
    "id": 64,
    "question": "69. 纸介质国家秘密载体，其密级和保密期限应在首页(或者封面)标明。               （  ）"
  },
  {
    "id": 65,
    "question": "70. 涉及国家秘密的地图、图纸、图表在其标题之后或者下方标明密级和保密期限。            （  ）"
  },
  {
    "id": 66,
    "question": "71. 文件、资料汇编中有密件的，应当对各独立密件的密级和保密期限做出国家秘密标志，并在封面或者首页以其中的最低密级和最短保密期限做出国家秘密标志。         （  ）"
  },
  {
    "id": 67,
    "question": "72. 摘录，引用密件中属于国家秘密的内容，应当以其中最高密级和最长保密期限做出国家秘密标志。       （√） 73. 密件的密级和保密期限变更后，应当在原国家秘密标志位置的附近做出新标志，原标志以明显方式废除。     （  ）"
  },
  {
    "id": 68,
    "question": "74. 在保密期限内解密的密件，应当以能够明显识别的方式标明解密的字样。              （  ）"
  },
  {
    "id": 69,
    "question": "75. 密品应当在壳体及封面，外包装的显著位置标注国家秘密标志，无法在物品本身标注或者不宜做出国家秘密标志的，应当在密品使用维护说明书中注明密级、保密期限和知悉范围，并提出相应的保密措施。                （√） 76. 保密工作机构应当组织相关涉密业务部门研究制定本单位《国家秘密事项范围细目》。          （  ）"
  },
  {
    "id": 70,
    "question": "77. 国家秘密事项的密级和保密期限一经确定，就不能改变。（  ）"
  },
  {
    "id": 71,
    "question": "78. 国家秘密的保密期限，除有特殊规定外，绝密级事项不超过20年，机密级事项不超过10年，秘密级事项不超过5年。 （  ）"
  },
  {
    "id": 72,
    "question": "79. 保密期限需要缩短的，由原确定密级和保密期限的机关、单位或者上级机关决定。            （  ）"
  },
  {
    "id": 73,
    "question": "80. 保密期限需要延长的，由原确定密级和保密期限的机关、单位或者上级机关决定。            （  ）"
  },
  {
    "id": 74,
    "question": "81. 单位领导要求继续保密的事项，在领导要求的期限内不得解密。                 （  ）"
  },
  {
    "id": 75,
    "question": "82.已解密的事项可以对全社会公开。      （  ）"
  },
  {
    "id": 76,
    "question": "83. 企业的技术成果被确定为国家秘密后，在保密期限内不得擅自解密和对外提供。            （  ）"
  },
  {
    "id": 77,
    "question": "84. 各级机关和涉密单位编发的内部工作简报都应定为国家秘密。                 （  ）"
  },
  {
    "id": 78,
    "question": "85. 密级的变更包括降低密级或者提高密级。    （  ）"
  },
  {
    "id": 79,
    "question": "86. 制作国家秘密载体应当依照有关规定标明密级和保密期限，注明发放范围及制作数量，并编排序号。      （√） 87. 纸介质国家秘密载体应当在本机关、本单位内部文印室或者交保密行政管理部门审查批准的单位制作。      （  ）"
  },
  {
    "id": 80,
    "question": "88. 国家秘密载体印制资质单位，使用电子方法排版印制或者打印国家秘密载体的，复制完成后其磁盘内的载体内容可以自行删除。                  （  ）"
  },
  {
    "id": 81,
    "question": "89. 收发国家秘密载体，应当履行清点、登记、编号、签收等手续。                 （  ）"
  },
  {
    "id": 82,
    "question": "90. 传递国家秘密载体应当密封包装，装载国家秘密载体的信封或者袋牌上应当标明密级、编号和收发件单位名称。   （  ）"
  },
  {
    "id": 83,
    "question": "91. 传递国家秘密载体应当通过机要交通、机要通信或者指派专人传递，不得通过普通邮政渠道传递。（  ）"
  },
  {
    "id": 84,
    "question": "92. 国家秘密文件、资料料可以通过普通邮政“特快专递”传送。                  （  ）"
  },
  {
    "id": 85,
    "question": "93. 不准通过普通邮政、快递传递属于国家秘密的文件、资料和其他物品。               （  ）"
  },
  {
    "id": 86,
    "question": "94.记录涉密内容应当使用保密本。       （  ）"
  },
  {
    "id": 87,
    "question": "95. 单位收到绝密级载体后应当按照规定的范围组织阅读和使用，并对接触和知悉绝密级国家秘密的人员做出文字记载。 （  ）"
  },
  {
    "id": 88,
    "question": "96. 单位内部复制国家秘密载体应当履行审批手续，复制机密级以上国家秘密载体须经部门或者单位领导批准，加盖复制戳记，视同原件管理，并进行登记。           （  ）"
  },
  {
    "id": 89,
    "question": "97. 因公出差，且两人同行，可以携带密件到购物、餐饮、娱乐等公共场所。              （  ）"
  },
  {
    "id": 90,
    "question": "98. 阅读，承办、使用密件，应当在符合保密要求的办公场所进行，严禁擅自携带外出。           （  ）"
  },
  {
    "id": 91,
    "question": "99. 传阅秘密公文的人员很多，逐人逐份登记很麻烦，有时可以不登记，收回时自已在文件登记本上画个勾就可以。   （  ）"
  },
  {
    "id": 92,
    "question": "100. 某协作单位工作人员因工作需要借阅协作范围内的绝密级图纸，该单位接待人员电话请示有关领导同意后，就可以为其办理借阅手续。                （  ）"
  },
  {
    "id": 93,
    "question": "101. 某领导携带涉密U盘参加行业工作会，会议要求报书面材料，因时间紧急，该领导就使用涉密U盘连接营业性场所计算机打印机密级汇报资料，打印完成后作删除处理即可。    （  ）"
  },
  {
    "id": 94,
    "question": "102. 某单位进行文件汇编工作时，少量摘抄某涉密文件，经办人员认为该文件汇编册不涉密，可不标注密级。     （  ）"
  },
  {
    "id": 95,
    "question": "103. 涉密人员参加会议带回的秘密文件、资料，应交本单位文秘部门或档案部门登记、管理。          （  ）"
  },
  {
    "id": 96,
    "question": "104.阅读和使用国家秘密载体应当办理登记、签收手续。管理人员应当随时掌握国家秘密载体的去向。       （  ）"
  },
  {
    "id": 97,
    "question": "105.传达国家秘密事项时，凡不准记录、录音、录像的，应当事先申明。                （  ）"
  },
  {
    "id": 98,
    "question": "106.不准在普通手机通话中涉及国家秘密。    （  ）"
  },
  {
    "id": 99,
    "question": "107.普通手机处于关机状态下，不存在泄密隐患。  （  ）"
  },
  {
    "id": 100,
    "question": "108. 不得使用普通手机短信传送国家秘密信息。   （  ）"
  },
  {
    "id": 101,
    "question": "109.不得使用普通手机中微信、QQ等社交软件谈论、传递国家秘密。                （  ）"
  },
  {
    "id": 102,
    "question": "110. 不得将普通手机与涉密信息系统连接。    （  ）"
  },
  {
    "id": 103,
    "question": "111. 不得在保密要害部门、部位使用普通手机。   （  ）"
  },
  {
    "id": 104,
    "question": "112. 个人因公外出，携带国家秘密载体应当采取严格的保密措施。                 （  ）"
  },
  {
    "id": 105,
    "question": "113. 因工作需要随身携带密件、密品外出时，不得进入购物、餐饮娱乐等公共场所。            （  ）"
  },
  {
    "id": 106,
    "question": "114. 领导干部为了工作方便，可以将密件带回家中处理。（  ）"
  },
  {
    "id": 107,
    "question": "115. 工作人员离开办公场所，应当将国家秘密载体存放在保密设备里。                （  ）"
  },
  {
    "id": 108,
    "question": "116. 涉密人员在办公场所阅读、承办、使用密件过程中，需要临时离开，无须将密件存放到保密柜中。       （×） 117. 绝密级秘密载体必须放置在安全可靠的密码保险柜中保存，并有专人管理。              （  ）"
  },
  {
    "id": 109,
    "question": "118. 销毁国家秘密载体，应当采用物理或者化学的方法彻底销毁，确保信息无法还原。           （  ）"
  },
  {
    "id": 110,
    "question": "119. 在不解密的情况下，机密级、秘密级国家秘密技术成果可以申请公开专利或者由保密专利转为公开专利。     （  ）"
  },
  {
    "id": 111,
    "question": "120. 公开报道、出版或者个人接受境外媒体采访涉及国家政治、经济、外交、科技、军事方面内容的，不用事先经过审批。 （  ）"
  },
  {
    "id": 112,
    "question": "121. 未经批准，严禁公开报道尚属国家秘密的武器装备技术性能指标、科研生产能力、结构布局、产量、发展规划等涉密内容。（  ）"
  },
  {
    "id": 113,
    "question": "122. 机关、单位每年应当定期对当年所存国家秘密载体进行清查、核对，发现问题的应当及时向保密工作机构报告。  （  ）"
  },
  {
    "id": 114,
    "question": "123. 销毁纸介质国家秘密载体应当采用焚毁、化浆等方法处理，使用碎纸机销毁的应当使用符合保密要求的碎纸机，送造纸厂销毁的应当送保密行政管理部门指定的造纸厂销毁，并由销毁单位两人以上押运、监销。              （  ）"
  },
  {
    "id": 115,
    "question": "124. U盘上的涉密信息，只要执行删除程序就不可恢复。 （  ）"
  },
  {
    "id": 116,
    "question": "125. 国家秘密载体不得作为废品出售。      （  ）"
  },
  {
    "id": 117,
    "question": "126. 已拆除硬盘的涉密计算机，可以赠送给希望小学使用。（  ）"
  },
  {
    "id": 118,
    "question": "127. 密品是指直接含有国家秘密信息，或者通过观察、测试、分析等手段能够获取所承载的国家秘密信息的设备和产品。  （  ）"
  },
  {
    "id": 119,
    "question": "128. 密品的研制、生产、保存和使用单位应当对密品的密级、保密期限、知悉范围、保密要点的内容进行登记，各环节的交接应当登记签收。                （  ）"
  },
  {
    "id": 120,
    "question": "129. 保密要害部门、部位由各机关、单位确定，报国家或者省、自治区、直辖市保密行政管理部门确认或者备案。    （  ）"
  },
  {
    "id": 121,
    "question": "130. 保密要害部门、部位应当具备完善可靠的人防、技防、物防措施。                （  ）"
  },
  {
    "id": 122,
    "question": "131. 涉密场所使用的进口设备和产品应当进行安全技术检测。                   （  ）"
  },
  {
    "id": 123,
    "question": "132. 保密要害部门、部位禁止使用无绳电话和普通手机，未经批准不得带入有录音、录像、拍照、信息存储功能的设备。  （  ）"
  },
  {
    "id": 124,
    "question": "133. 普通手机关机后可以带入要害部门、部位。   （  ）"
  },
  {
    "id": 125,
    "question": "134. 涉密电子文档应当标注国家秘密标志，国家秘密标志不能与正文分离。              （  ）"
  },
  {
    "id": 126,
    "question": "135. 不得在涉密计算机和非涉密计算机上交叉使用移动存储介质。                 （  ）"
  },
  {
    "id": 127,
    "question": "136. 不得使用未采取密码保护的通信系统传输涉密信息。（  ）"
  },
  {
    "id": 128,
    "question": "137. 不得将自己使用的涉密计算机和移动存储介质擅自交给他人使用。                （  ）"
  },
  {
    "id": 129,
    "question": "138. 无线电话不保密，军线电话是保密的。    （  ）"
  },
  {
    "id": 130,
    "question": "139. 数字移动电话传输的是数字信号，因此是保密的。 （  ）"
  },
  {
    "id": 131,
    "question": "140. 在保密通信技术较落后的情况下，允许在单位内部无保密措施的电话中传递国家秘密。          （  ）"
  },
  {
    "id": 132,
    "question": "141. 电磁信号泄漏泄密的方式主要是辐射和传导两种方式。（  ）"
  },
  {
    "id": 133,
    "question": "142. 涉密存储介质经文件删除并格式化处理后，仍不得作为非密介质使用。              （  ）"
  },
  {
    "id": 134,
    "question": "143. 利用现代通信及计算机网络远程传输国家秘密信息，必须采用密码保护措施，并禁止密明混用。       （√） 144. 涉密信息使用的加密措施应当经过国家密码主管部门批准，在任何地方都可以使用。           （  ）"
  },
  {
    "id": 135,
    "question": "145. 涉密信息使用的加密措施须经国家密码主管部门批准，并与所保护的信息密级等级相符合。        （  ）"
  },
  {
    "id": 136,
    "question": "146. 绝密级信息必须加密存储。        （  ）"
  },
  {
    "id": 137,
    "question": "147. 涉密计算机不安装使用无线键盘、无线鼠标、蓝牙、红外设备和无线网卡。              （  ）"
  },
  {
    "id": 138,
    "question": "148. 涉密便携式计算机应当拆除具有无线联网功能的硬件模块。                  （  ）"
  },
  {
    "id": 139,
    "question": "149. 无线联网功能硬件模块无法拆除的计算机禁止作为涉密计算机和信息系统的服务器、用户终端使用。      （√） 150. 涉密计算机不得安装来历不明的软件和随意拷贝他人文件。                  （  ）"
  },
  {
    "id": 140,
    "question": "151. 涉密计算机和移动存储介质应在保密行政管理部门设立的销毁工作机构或者保密行政管理部门指定的单位销毁。  （  ）"
  },
  {
    "id": 141,
    "question": "152. 在涉密场所使用的与国际互联网或者其他公共网络连接的计算机不得安装视频、音频等输入装置。      （√） 153. 不得在连接国际互联网的计算机上存储和处理涉密信息。                   （  ）"
  },
  {
    "id": 142,
    "question": "154. 涉密计算机不得与国际互联网络或者其他公共信息网络相连接。                （  ）"
  },
  {
    "id": 143,
    "question": "155. 确因工作需要，可以使用私人计算机处理涉密文件，但要与国际互联网断开连接，待处理完涉密信息后可与互联网连接。（  ）"
  },
  {
    "id": 144,
    "question": "156. 任何单位和个人均不得在国际互联网网络主页、电子公告栏、聊天室、网络新闻组、微博上发布、谈论、张贴、传播国家秘密信息。                （  ）"
  },
  {
    "id": 145,
    "question": "157. 为节约开支，可以将淘汰的涉密计算机交本单位非涉密部门使用。                （  ）"
  },
  {
    "id": 146,
    "question": "158. 涉密信息系统不得直接或者间接连接国际互联网，必须实行物理隔离。              （  ）"
  },
  {
    "id": 147,
    "question": "159. 国家秘密信息不得在与国际互联网连接的计算机和信息系统中存储、处理、传递，但可以在单位内部非涉密单机上存储、处理、传递。                （  ）"
  },
  {
    "id": 148,
    "question": "160. 召开涉及国家秘密的会议，使用无线扩音、通信设备不能把音量开得太大。              （  ）"
  },
  {
    "id": 149,
    "question": "161. 对参与国家秘密技术研制的科技人员，有关单位不得因其成果不宜公开发表、交流、推广而影响其评奖、表彰和职称的评定。                  （  ）"
  },
  {
    "id": 150,
    "question": "162. 在对外经济合作中，凡涉及国家秘密的资料未经保密审查和批准，一律不得对外提供。          （  ）"
  },
  {
    "id": 151,
    "question": "163. 在对外交往与合作中急需提供国家秘密事项的，可以先提供，后补办手续。             （  ）"
  },
  {
    "id": 152,
    "question": "164.对外交流中除交流内容与谈判口径外，所提供资料和产品应当经过保密审查。            （  ）"
  },
  {
    "id": 153,
    "question": "165.对外公开新闻宣传时，单位代号、真实名称、掩护名称不得同时使用。               （  ）"
  },
  {
    "id": 154,
    "question": "166.接受媒体采访，一般不得涉及国家秘密，特殊情况需要涉及国家秘密的，应当办理审批手续。        （  ）"
  },
  {
    "id": 155,
    "question": "167.音像制品涉及国家秘密的，应按照涉密资料保管。 （  ）"
  },
  {
    "id": 156,
    "question": "168. 保密教育和保密提醒是科技交流必须坚持的制度。 （  ）"
  },
  {
    "id": 157,
    "question": "169. 对外科技交流活动不得涉及国家秘密，确需涉及国家秘密的应当履行审批手续。            （  ）"
  },
  {
    "id": 158,
    "question": "170. 未经批准，任何单位、部门或者个人均不得到保密要害部门、部位进行采访、照相、录像等活动。        （√） 171. 使国家秘密被不应知悉者知悉的，属于泄露国家秘密行为。                  （  ）"
  },
  {
    "id": 159,
    "question": "172. 发现国家秘密载体在使用中下落不明，应当在8小时内向本单位保密工作机构报告，向上级报告不应超过24小时。 （  ）"
  },
  {
    "id": 160,
    "question": "173. 国家秘密载体下落不明，自发现之日起，绝密级载体10日内、机密级、秘密载体60日内查无结果的，按照泄密事件处理。（  ）"
  },
  {
    "id": 161,
    "question": "174. 报告泄密事件应当包括被泄露国家秘密的内容、密级、数量及其载体形式、事件发现经过、责任人基本情况、发生的时间、地点及经过。               （  ）"
  },
  {
    "id": 162,
    "question": "175.将涉及国家秘密的计算机和计算机信息系统与国际互联网连接，泄露国家秘密的，应立为泄密案件。      （√） 176. 过失泄露一项绝密级国家秘密的可不予立案，在单位内部处理。                （  ）"
  },
  {
    "id": 163,
    "question": "177. 违反《中华人民共和国保守国家秘密法》规定，泄露国家秘密，不够刑事处罚的，可以酌情给予行政处分。    （√） 178. 以窃取、刺探、收买的方法，非法获取国家秘密的，都应当依据《刑法》追究其刑事责任。        （  ）"
  },
  {
    "id": 164,
    "question": "179. 发生泄密事件的机关、单位不及时上报或者隐匿不报的，视情节和造成的后果追究有关人员或者领导人的责任。  （  ）"
  },
  {
    "id": 165,
    "question": "180. 未经相应工作部门批准，不得向境外邮寄密品、密件或者随身携带密品、密件出境。          （  ）"
  },
  {
    "id": 166,
    "question": "1. 制定《武器装备科研生产单位保密资格认定办法》的目的是进一步规范和加强武器装备科研生产单位保密资格认定工作，确保国家秘密安全。               （  ）"
  },
  {
    "id": 167,
    "question": "2. 《武器装备科研生产单位保密资格认定办法》(国保发〔2016〕15号）自2016年6月1日起施行。2008年12月31日印发的《武器装备科研生产单位保密资格审查认证管理办法》(国保发〔2008〕8号)同时废止。               （  ）"
  },
  {
    "id": 168,
    "question": "3. 《武器装备科研生产单位保密资格认定办法》适用于承担涉密武器装备科研生产任务的企业事业单位保密资格认定工作。 （  ）"
  },
  {
    "id": 169,
    "question": "4. 已承担涉密武器装备科研生产任务的企业事业单位，申请更高级别保密资格，可以免于现场审查。       （  ）"
  },
  {
    "id": 170,
    "question": "5. 未取得保密资格的企业事业单位不能承担任何涉密武器装备科研生产任务。              （  ）"
  },
  {
    "id": 171,
    "question": "6. 武器装备科研生产一级保密资格单位，可以承担绝密级、机密级、秘密级的科研生产任务。          （  ）"
  },
  {
    "id": 172,
    "question": "7. 武器装备科研生产二级保密资格单位，可以承担机密级、秘密级科研生产任务。             （  ）"
  },
  {
    "id": 173,
    "question": "8. 武器装备科研生产三级保密资格单位，可以承担机密级、秘密级科研生产任务。             （  ）"
  },
  {
    "id": 174,
    "question": "9. 取得保密资格的单位都应当被列入《武器装备科研生产单位保密资格名录》。             （  ）"
  },
  {
    "id": 175,
    "question": "10. 申请一、二、三级保密资格的企业事业单位都应当由国家军工保密资格认定委员会进行现场审查。       （×） 11.凡是雇佣外籍人员的单位都不能申请保密资格。  （  ）"
  },
  {
    "id": 176,
    "question": "12. 申请保密资格的单位，1年内未发生严重泄密事件，才具备申请保密资格的基本条件。          （  ）"
  },
  {
    "id": 177,
    "question": "13. 取得保密资格的单位，资本构成、单位性质发生重大变化的，应当于发生后60个工作日内重新申请。       （×） 14. 被注销、暂停、撤销保密资格的单位，自行政决定下发之日起，不得签订新的涉密武器装备科研生产任务合同。   （  ）"
  },
  {
    "id": 178,
    "question": "15. 某公司具备申请保密资格的基本条件，但2015年8月18日发生过一起泄密事件，因此，该公司只能到2016年8月18日以后才能申请保密资格。             （  ）"
  },
  {
    "id": 179,
    "question": "16. 现场审查结果分为“通过”“不通过”或者“中止”。（  ）"
  },
  {
    "id": 180,
    "question": "17. 现场审查时应当抽取10-30名涉密人员进行保密知识开卷测试。                 （  ）"
  },
  {
    "id": 181,
    "question": "18. 现场审查时，审查组应当对被审查单位的所有涉密人员进行保密知识测试。              （  ）"
  },
  {
    "id": 182,
    "question": "19. 现场审查结束后，审查组应当向被审查单位通报审查意见和结论，对存在的问题提出整改要求。        （√） 20. 现场审查时发现被审查单位达不到《评分标准》所列基本项要求的，应当中止审查，并要求其采取整改措施。    （  ）"
  },
  {
    "id": 183,
    "question": "21. 现场审在中止的单位，3个月内不重新进行现场审查。（  ）"
  },
  {
    "id": 184,
    "question": "22. 被撤销保密资格的单位，已签订有效合同的，在采取有效保密措施。确保安全保密的情况下可以继续履行合同。   （  ）"
  },
  {
    "id": 185,
    "question": "23. 现场审查中止的单位经过3个月整改后，审查组应当恢复审查。                 （  ）"
  },
  {
    "id": 186,
    "question": "24. 取得保密资格的单位应当实行年度自检制度，每年1月31日前，向作出审批决定的行政机关报送上一年度单位基本情况变化和保密资格标准落实情况自检报告。         （  ）"
  },
  {
    "id": 187,
    "question": "25. 对已经取得保密资格满1年的单位。国家和省、自治区、直辖市军工保密资格认定委员会应当进行复查。     （×） 26.省、自治区、直辖市军工保密资格认定委员会对已经取得保密资格单位进行复查时，如果发现被复查单位达不到《评分标准》所列基本项要求的，应当中止复查。        （  ）"
  },
  {
    "id": 188,
    "question": "27. 对取得保密资格的单位进行复查时，如果发现被复查单位个别基本项达不到要求，应当视情给予警告、通报、约谈主要负责人，并限期整改。              （  ）"
  },
  {
    "id": 189,
    "question": "28. 未通过复查的单位，3个月后重新复查仍未通过的，将撤销其保密资格。              （  ）"
  },
  {
    "id": 190,
    "question": "29. 取得保密资格的单位，把涉密武器装备科研生产任务分包给不具有相应保密资格的单位，国家军工保密资格认定委员会将责令其终止分包合同，并限期整改。          （  ）"
  },
  {
    "id": 191,
    "question": "30. 已经取得保密资格的单位，选择不具有相应等级保密资格的单位分包涉密武器装备科研生产任务的，除按照规定撤销其保密资格以外，构成犯罪的，要依法追究刑事责任。      （  ）"
  },
  {
    "id": 192,
    "question": "31. 取得保密资格的单位，末按照规定进行年度自检的，收回其保密资格证书，撤销其保密资格。        （  ）"
  },
  {
    "id": 193,
    "question": "32. 被撤销保密资格的单位，1年内不受理其申请。  （  ）"
  },
  {
    "id": 194,
    "question": "33. 取得保密资格的单位，如果擅自引入外商投资的，将撤销其保密资格。               （  ）"
  },
  {
    "id": 195,
    "question": "34. 取得保密资格的单位，如果擅自雇佣外籍人员的，应解雇外籍人员，并进行整改            （  ）"
  },
  {
    "id": 196,
    "question": "35.取得保密资格的单位存在重大泄密隐患时，应当撤销该单位的保密资格。              （  ）"
  },
  {
    "id": 197,
    "question": "1. 《武器装备科研生产单位一级保密资格标准》是对申请一级保密资格的单位进行审查认定和复查的依据。      （  ）"
  },
  {
    "id": 198,
    "question": "2. 《武器装备科研生产单位二级保密资格标准》是对申请二级保密资格的单位进行审查认定和复查的依据。      （  ）"
  },
  {
    "id": 199,
    "question": "3. 《武器装备科研生产单位三级保密资格标准》是对申请三级保密资格的单位进行审查认定和复查的依据。      （  ）"
  },
  {
    "id": 200,
    "question": "4. 《武器装备科研生产单位保密资格标准》的实施要求之一是“积极防范，突出重点，严格标准，严格管理”。    （×） 5. 《武器装备科研生产单位保密资格标准》的实施要求之一是“积极防范，突出重点，严格标准，依法管理”。    （√） 6. 《武器装备科研生产单位保密资格标准》的实施要求之一是“业务工作谁主管，保密工作谁负责，促进保密工作与业务工作相融合”。                （  ）"
  },
  {
    "id": 201,
    "question": "7. 保密责任主体是单位法定代表人或者主要负责人，分管保密工作负责人、其他负责人、涉密部门或者项目负责人、涉密人员。（  ）"
  },
  {
    "id": 202,
    "question": "8. 保密责任主体是分管保密工作负责人和保密工作机构。（  ）"
  },
  {
    "id": 203,
    "question": "9. 单位其他负责人，应当对分管工作中的保密措施落实情况进行监督检查。              （  ）"
  },
  {
    "id": 204,
    "question": "10. 刘教授是某涉密项目负责人，组织好本项目研究是他的责任，对本项目研究中的保密工作监督检查是单位分管保密工作领导和保密工作机构的责任。            （  ）"
  },
  {
    "id": 205,
    "question": "11. 某单位取得二级保密资格，在承担某涉密科研生产任务过程中发生泄密事件，除追究直接责任人和主管业务负责人的责任外，单位法定代表人也应当承组相应的责任。       （  ）"
  },
  {
    "id": 206,
    "question": "12. 实行保密责任考核追究是落实保密工作责任制的有效措施。                  （  ）"
  },
  {
    "id": 207,
    "question": "13. 保密工作机构是指单位保密委员会(保密工作领导小组)。                   （  ）"
  },
  {
    "id": 208,
    "question": "14. 保密工作机构是专门负责保密管理工作的职能部门，独立行使保密管理职能。             （  ）"
  },
  {
    "id": 209,
    "question": "15. 申请或者取得保密资格的单位应当成立保密委员会或者保密工作领导小组。             （  ）"
  },
  {
    "id": 210,
    "question": "16. 按照《武器装备科研生产单位保密资格评分标准》规定，保密工作机构设置不符合标准要求的，应当中止审查或者复查。（  ）"
  },
  {
    "id": 211,
    "question": "17. 单位保密委员会(保密工作领导小组)负责人是通过选举产生或者上级单位指派的。           （  ）"
  },
  {
    "id": 212,
    "question": "18. 申请或者取得三级保密资格的单位可以成立保密委员会。                   （  ）"
  },
  {
    "id": 213,
    "question": "19. 一级保密资格单位保密委员会主任由单位负责人担任。（  ）"
  },
  {
    "id": 214,
    "question": "20. 二级保密资格单位保密委员会主任(保密工作领导小组组长)由单位负责人担任。            （  ）"
  },
  {
    "id": 215,
    "question": "21. 三级保密资格单位保密委员会主任(保密工作领导小组组长)由单位负责人担任。            （  ）"
  },
  {
    "id": 216,
    "question": "22. 一级保密资格单位涉密人员超过100人(含)的，应当确定1名部门负责人担任保密工作机构负责人，配备1名专职保密工作人员。                 （  ）"
  },
  {
    "id": 217,
    "question": "23. 一级保密资格单位涉密人员100人(含)以上的，应当设置专门负责保密管理工作的职能部门。        （  ）"
  },
  {
    "id": 218,
    "question": "24. 二级保密资格单位涉密人员200人(含)以上的，应当设置专门负责保密管理工作的职能部门。        （  ）"
  },
  {
    "id": 219,
    "question": "25. 专职保密工作人员是指制作、传递和管理国家秘密载体的人员。                 （  ）"
  },
  {
    "id": 220,
    "question": "26. 一级保密资格单位涉密人员1000人(含)以上的，保密工作机构专职人员配备不得少于3人。        （  ）"
  },
  {
    "id": 221,
    "question": "27. 二级保密资格单位涉密人员1000人(含)以上的，保密工作机构专职人员配备不得少于4人。        （  ）"
  },
  {
    "id": 222,
    "question": "28. 管理多个法人单位的，其保密工作机构人员配备按照所管理单位涉密人员总数计算。           （  ）"
  },
  {
    "id": 223,
    "question": "29. 某公司申请一级保密资格，涉密人员1205人，已按照规定配备4名专职保密工作人员。保密处要求将其中一人调配为保密技术管理人员，但单位主要领导认为保密工作技术含量低，可以不配保密技术管理人员。              （  ）"
  },
  {
    "id": 224,
    "question": "30. 专职保密工作人员2人(含)以上的，应当配备1名保密技术管理人员。               （  ）"
  },
  {
    "id": 225,
    "question": "31. 基本制度是指单位依据国家保密法律法规制定的日常保密管理总的工作规范。            （  ）"
  },
  {
    "id": 226,
    "question": "32. 单位各职能部门应当将保密管理要求融入业务工作制度中，并组织落实。              （  ）"
  },
  {
    "id": 227,
    "question": "33. 重大涉密工程或者项目应当制定专项保密制度。  （  ）"
  },
  {
    "id": 228,
    "question": "34. 某公司具有一级保密资格。已根据工作需要制定保密工作基本制度，公司领导认为内设机构设有必要再制定业务制度和专项制度，这样既便于管理，又节省人力、物力。      （  ）"
  },
  {
    "id": 229,
    "question": "35. 单位保密工作机构对定密工作负主要责任。   （  ）"
  },
  {
    "id": 230,
    "question": "36. 单位主管业务领导、业务部门负有定密工作的主要责任，保密工作机构负有定密工作的组织协调和监督指导的职责。  （  ）"
  },
  {
    "id": 231,
    "question": "37. 界定涉密岗位和涉密人员涉密等级的依据是“以项定岗，以岗定人”，即依据任务或者合同项目原始密级和有关保密范围确定岗位及人员的涉密等级。            （  ）"
  },
  {
    "id": 232,
    "question": "38. 承担机要、档案、密码通信等涉密业务管理的工作人员，不属于专职保密工作人员。           （  ）"
  },
  {
    "id": 233,
    "question": "39. 国家秘密事项在军工科研生产任务期内不需要继续保密的，应当及时解密。              （  ）"
  },
  {
    "id": 234,
    "question": "40. 一个人在涉密工作岗位上干得年限越长，知道的国家秘密就越多，因此，应当根据个人在涉密岗位的工作年限确定涉密等级。（  ）"
  },
  {
    "id": 235,
    "question": "41. 工作中只要接触绝密级事项的人员，应当被确定为核心涉密人员。                （  ）"
  },
  {
    "id": 236,
    "question": "42. 工作中经常处理、产生、知悉和掌握绝密级事项的人员，应当被确定为核心涉密人员。          （  ）"
  },
  {
    "id": 237,
    "question": "43. 单位聘用涉密人员，不必与其签订保密承诺书，只需在聘用合同上明确保密要求就行。          （  ）"
  },
  {
    "id": 238,
    "question": "44. 单位聘用涉密人员要坚持先审后用的原则，应当进行保密培训并签订保密承诺书。            （  ）"
  },
  {
    "id": 239,
    "question": "45. 对涉密人员的保密管理不只是对涉密人员上岗前的保密审查和培训，还应包括在岗、离岗保密管理。      （√） 46. 单位应当每年对涉密人员进行考核，考核不合格的，应当及时调离涉密岗位。             （  ）"
  },
  {
    "id": 240,
    "question": "47. 涉密人员严重违反保密制度的，应当及时调离涉密岗位。（  ）"
  },
  {
    "id": 241,
    "question": "48. 取得三级保密资格的单位，每年对涉密人员进行保密教育培训应当每人不于15学时。           （  ）"
  },
  {
    "id": 242,
    "question": "49. 取得一级保密资格的单位，每年对涉密人员进行保密教育培训应当每人不少于15学时。          （  ）"
  },
  {
    "id": 243,
    "question": "50. 取得二级保密资格的单位，每年对涉密人员进行保密教育培训应当每人不少于15学时。          （  ）"
  },
  {
    "id": 244,
    "question": "51. 取得三级保密资格的单位，每年对涉密人员进行保密教育培训应当为每人不少于8学时。          （  ）"
  },
  {
    "id": 245,
    "question": "52. 为确保国家秘密安全，取得保密资格单位的涉密人员不允许因私出国(境)。              （  ）"
  },
  {
    "id": 246,
    "question": "53. 涉密人员因私出国(境)，应当按照规定履行审批手续。（  ）"
  },
  {
    "id": 247,
    "question": "54. 朱某是某单位的核心涉密人员，2006年8月20日从单位退休，按照国家有关规定，2009年8月20日之前朱某不能到拟聘用他的外资企业做顾问。            （  ）"
  },
  {
    "id": 248,
    "question": "55. 孙某是某单位的一般涉密人员，2007年3月10日从单位辞职后，2008年3月10日之前，他不能到境外机构工作。  （  ）"
  },
  {
    "id": 249,
    "question": "56. 涉密人员脱离单位，都应当与原单位签订保密承诺书。（  ）"
  },
  {
    "id": 250,
    "question": "57. 凡是国家秘密载体，包括已经定稿或者未定稿的文件和电子文档，都应当按照有关规定标明密级和保密期限。    （  ）"
  },
  {
    "id": 251,
    "question": "58. 制作、收发、传递、使用、复制、保存、维修和销毁国家秘密载体(含纸介质、磁介质和光盘等各类物品)及其过程文件、资料，应当符合国家有关保密管理规定。        （  ）"
  },
  {
    "id": 252,
    "question": "59. 应当根据工作需要，控制国家秘密载体的接触范围。 （  ）"
  },
  {
    "id": 253,
    "question": "60. 绝密级国家秘密载体应当存放在密码文件柜中。  （  ）"
  },
  {
    "id": 254,
    "question": "61. 涉密人员调入其他部门工作，涉密等级和岗位职责发生变化，其使用过的涉密计算机也必须一并带入新部门。   （  ）"
  },
  {
    "id": 255,
    "question": "62. 涉及国家秘密但未定稿的过程文件，可以不按国家秘密载体管理。                （  ）"
  },
  {
    "id": 256,
    "question": "63. 某涉密课题组负责人外出开会需携带一份涉密文件，他找单位保密员借出文件并复印登记后携带外出。      （  ）"
  },
  {
    "id": 257,
    "question": "64. 某涉密人员认为由其使用和管理的移动存储介质中存储大量秘密级信息和一份机密级信息，该介质应当定为秘密级载体。（  ）"
  },
  {
    "id": 258,
    "question": "65. 密品在研制、生产、试验、运输、保存、维修、使用过程中应当符合国家有关保密管理规定。        （  ）"
  },
  {
    "id": 259,
    "question": "66. 涉密人员辞职、解聘、调离涉密岗位，应当在离岗前清退保管和使用的国家秘密载体。          （  ）"
  },
  {
    "id": 260,
    "question": "67. 一级保密资格单位的保密要害部门应当实行区域隔离，并采取出入口控制、入侵报警、视频监控等技防措施。    （  ）"
  },
  {
    "id": 261,
    "question": "68. 二级保密资格单位的保密要害部门应当采取物理防护，并采取出入口控制、入侵报警、视频监控等技防措施。（  ）"
  },
  {
    "id": 262,
    "question": "69. 涉及保密要害部门、部位的工程建设项目要符合安全保密要求，所采取的保密防护措施应当经过单位保密工作机构审核，与工程项目同侧、同设计、同建设、同验收。（  ）"
  },
  {
    "id": 263,
    "question": "70. 携带涉密计算机和移动存储介质外出只要履行审批手续，若带出期间没有使用过，带回后可以不进行保密检查。 （  ）"
  },
  {
    "id": 264,
    "question": "71. 涉密信息系统应当配备系统管理员、安全保密管理员、安全审计员，三员角色可以兼任。 （  ）"
  },
  {
    "id": 265,
    "question": "72. 没有涉密信息系统的单位可以不配备涉密计算机安全保密管理员。 （  ）"
  },
  {
    "id": 266,
    "question": "73. 涉密信息系统与互联网及其他公共信息网络也可以实行逻辑隔离。 （  ）"
  },
  {
    "id": 267,
    "question": "74. 打印机只是输出设备，所以同一台打印机可以根据需要连接在涉密计算机或者非涉密计算机上使用。（  ）"
  },
  {
    "id": 268,
    "question": "75. 将手机关机后连接到涉密计算机上充电，不会破坏物理隔离。 （  ）"
  },
  {
    "id": 269,
    "question": "76. 存储机密级信息的硬盘经格式化后，可以降密或者解密使用。 （  ）"
  },
  {
    "id": 270,
    "question": "77. 机密级计算机口令长度不得少于6个字符，更换周期不得长于1个月。（  ）"
  },
  {
    "id": 271,
    "question": "78. 涉密计算机屏幕保护等待时间不得少于10分钟。（  ）"
  },
  {
    "id": 272,
    "question": "79. 涉密计算机的硬盘发生故障，因为还在保修期内，可以送到厂家进行维修或者更换。（  ）"
  },
  {
    "id": 273,
    "question": "80. 小张的秘密级U盘发生故障不能使用，他就使用铁锤将其砸碎，这样处理就符合物理销毁的保密要求。（  ）"
  },
  {
    "id": 274,
    "question": "81. 涉密计算机因性能不满足使用要求而淘汰，将硬盘和存储部件拆除后，可以捐赠给希望小学使用。 （  ）"
  },
  {
    "id": 275,
    "question": "82. 存储机密级信息的U盘经格式化后，可以降密或者解密使用。 （  ）"
  },
  {
    "id": 276,
    "question": "83. 涉及国家秘密的办公自动化设备可以联入单位非涉密信息系统。 （  ）"
  },
  {
    "id": 277,
    "question": "84. 重要涉密场所禁止使用普通手机和无绳电话。（  ）"
  },
  {
    "id": 278,
    "question": "85. 禁止使用非涉密办公自动化设备存储和处理涉密信息。（  ）"
  },
  {
    "id": 279,
    "question": "86. 计算机仅存储一份涉密信息，可以不确定为涉密计算机。 （  ）"
  },
  {
    "id": 280,
    "question": "87. 计算机密级计算机的身份鉴别如釆用用户名加口令的方式，则口令长度应当是十位以上，并以字母、数字和特殊字符混合排列。 （  ）"
  },
  {
    "id": 281,
    "question": "88. 秘密级计算机的身份鉴别如釆用用户名加口令的方式，则口令应当每月更换一次。 （  ）"
  },
  {
    "id": 282,
    "question": "89. 涉密计算机如釆用USB Key或者1C卡作为身份鉴别工具，拔除USB Key或者1C卡就进入黑屏状态，则可以在操作系统中不设置重鉴别方式（屏幕保护)。 （  ）"
  },
  {
    "id": 283,
    "question": "90. 涉密便携式计算机一般不存储涉密信息，所以涉密便携式计算机丢失不须追究其失密责任。 （  ）"
  },
  {
    "id": 284,
    "question": "91. 带有摄像头的便携式计算机，只要禁止使用摄像功能，就可以作为涉密便携式计算机使用。 （  ）"
  },
  {
    "id": 285,
    "question": "92. 涉密计算机使用的耳机只接收播放的音乐信号，不传递其他信息，所以可以使用无线耳机。（  ）"
  },
  {
    "id": 286,
    "question": "93. 某单位涉密计算机都是单机管理，—部门为了工作方便自行将部门内几台计算机通过集线器连接，用于共享文件和打印共享。 （  ）"
  },
  {
    "id": 287,
    "question": "94. 为保证自己使用的涉密计算机不受到计算机病毒和恶意代码的攻击，小王经常使用自己的U盘升级计算机病毒和恶意代码样本库。 （  ）"
  },
  {
    "id": 288,
    "question": "95. 将涉密U盘挂在身上，时刻处于自己的监控之中，符合保密要求。 （  ）"
  },
  {
    "id": 289,
    "question": "96. 同一个单位内，涉密等级都相同的人，涉密移动存储介质可以交叉使用。 （  ）"
  },
  {
    "id": 290,
    "question": "97. 机密级以上的涉密计算机，应当釆取USB移动存储介质绑定的保护措施。 （  ）"
  },
  {
    "id": 291,
    "question": "98. 携带涉密计算机和存储介质外出期间，为保证安全，应当将涉密计算机和存储介质分由不同的人员管理。（×） 99. 禁止使用连接国际互联网和其他公共信息网络的信息设备存储和处理涉密信息。 （  ）"
  },
  {
    "id": 292,
    "question": "100. 信息设备只要不连接国际互联网和其他公共信息网络，就可以处理涉密信息。 （  ）"
  },
  {
    "id": 293,
    "question": "101. 为充分利用资源，可以将单台扫描仪连接涉密计算和非涉密计算机使用。（  ）"
  },
  {
    "id": 294,
    "question": "102. 应当根据工作需要，配备专供外出携带的涉密计算机和存储介质，并由专人进行集中管理。 （  ）"
  },
  {
    "id": 295,
    "question": "103. 多人使用同一台涉密计算机，每个人对该涉密计算机有相同的使用和管理权限。 （  ）"
  },
  {
    "id": 296,
    "question": "104. 涉密信息设备的报废应当拆除涉密存储部件，将剩余部分作报废处理。 （  ）"
  },
  {
    "id": 297,
    "question": "105. 非涉密信息设备不需要专人管理。 （  ）"
  },
  {
    "id": 298,
    "question": "106. 涉密场所的无绳电话，只要不使用，就不会产生泄密隐患。 （  ）"
  },
  {
    "id": 299,
    "question": "107. 涉密信息设备可以联入单位非涉密的内部办公信息系统。 （  ）"
  },
  {
    "id": 300,
    "question": "108. 信息设备应当粘贴标识，标明密级或者使用用途。（  ）"
  },
  {
    "id": 301,
    "question": "109. 按照《武器装备科研生产单位保密资格评分标准》规定，涉密信息系统未通过国家保密行政管理部门设立或者授权测评机构的系统测评并存储、处理涉密信息的，中止审查或者复查。 （  ）"
  },
  {
    "id": 302,
    "question": "110. 涉密信息设备或者信息存储设备连接公共信息网络的，中止审查或者复查。 （  ）"
  },
  {
    "id": 303,
    "question": "111. 处理涉密信息的信息设备连接国际互联网或者其他公共信息网络的，中止审查或者复查。 （  ）"
  },
  {
    "id": 304,
    "question": "112. 使用连接国际互联网或者其他公共信息网络的信息设备处理涉密信息的，中止审查或者复查。 （  ）"
  },
  {
    "id": 305,
    "question": "113. 将手机和传真机接入涉密计算机和涉密信息系统，就破坏了物理隔离。 （  ）"
  },
  {
    "id": 306,
    "question": "114. 涉密会议正在进行，麦克风出现问题，服务人员马上取来一支无线麦克风，使会议继续进行。（  ）"
  },
  {
    "id": 307,
    "question": "115. 由上级单位宣传部门通知的涉及军品科研生产事项的新闻媒体采访，可以不履行审批手续。（  ）"
  },
  {
    "id": 308,
    "question": "116. 涉密军工单位内部的新闻宣传专栏、刊物登载的新闻宣传材料不需要进行保密审查。（  ）"
  },
  {
    "id": 309,
    "question": "117. 张某2007年5月从一所二级保密资格高校退休，2007年8月他把自己工作期间从事军品研究的成果写成专著准备出版，张某认为他已退休，其专著属于个人成果，不需要再由单位进行保密审查。 （  ）"
  },
  {
    "id": 310,
    "question": "118. 涉密会议应当在具备安全保密条件的场所召开，重要涉密会议应当在内部场所召开。重要涉密会议主办部门应制定保密方案，落实保密措施，必要时保密工作机构应当派人监督和检查。（  ）"
  },
  {
    "id": 311,
    "question": "119. 王某参加涉密会议时，为了便于发言和整理相关资料，他带一台具有无线上网功能的便携式计算机进入会场，会议主办方也没有提出异议。（  ）"
  },
  {
    "id": 312,
    "question": "120. 甲公司为某项涉密武器装备外场试验任务牵头单位，另有3家公司参加。因此，试验现场的保密管理工作由甲公司负责组织协调。 （  ）"
  },
  {
    "id": 313,
    "question": "121. 分包涉密项目，必须选择具有保密资格的单位。（  ）"
  },
  {
    "id": 314,
    "question": "122. 《武器装备科研生产许可目录》之外的应急或者短期生产的机密级、秘密级涉密项目，选择非保密资格单位的，分包单位就当按照有关保密规定和程序对承制方进行保密审查，签订保密协议，提出保密要求，履行保密监制管责任。（  ）"
  },
  {
    "id": 315,
    "question": "123. 分包涉密项目，没有选择相应保密资格的单位，加重扣分。（  ）"
  },
  {
    "id": 316,
    "question": "124. 按照《武器装备科研生产单位保密资格评分标准》规定，选择的协作配套单位不具有相应保密资格的，应当中止审查或者复查。 （  ）"
  },
  {
    "id": 317,
    "question": "125. 军工单位在对外交流、合作和谈判等外事活动应当制定保密方案，明确保密事项，采取相应的保密措施，执行保密提醒制度。 （  ）"
  },
  {
    "id": 318,
    "question": "126. 对外交流内容、谈判口径、提供资料和产品应当经过保密审查；涉及国家秘密的，应当按照有关规定履行审批程序。 （  ）"
  },
  {
    "id": 319,
    "question": "127. 涉密部门和涉密人员应当每月进行保密自查，自查及整改情况报单位保密工作机构。 （  ）"
  },
  {
    "id": 320,
    "question": "128. 单位应当每半年组织一次保密检查。 （  ）"
  },
  {
    "id": 321,
    "question": "129. 保密委员会年度内应当组织对单位负责人的保密检查。 （  ）"
  },
  {
    "id": 322,
    "question": "130. 单位发生泄密事件应当按照有关规定及时报告和采取补救措施，并报告查处情况。 （  ）"
  },
  {
    "id": 323,
    "question": "131. 保密工作责任落实情况应当纳人绩效考核，严格执行保密工作责任追究。 （  ）"
  },
  {
    "id": 324,
    "question": "132. 专项保密工作经费用于保密防护设施的建设和设备的配备。 （  ）"
  },
  {
    "id": 325,
    "question": "133. 专项保密工作经费应当列入单位年度财务预算，根据工作需要足额开支。 （  ）"
  },
  {
    "id": 326,
    "question": "134. 保密管理工作经费用于单位日常保密管理工作。（  )"
  },
  {
    "id": 327,
    "question": "135. 保密工作档案由保密工作机构和业务部门按照职责分工分别建立。 （  ）"
  },
  {
    "id": 328,
    "question": "136. 保密工作档案保存期限一般不少于2年。 （  ）"
  },
  {
    "id": 329,
    "question": "137. 按照《武器装备科研生产单位保密资格评分标准》的规定，达不到重点项要求的，加重扣分。 （  ）"
  },
  {
    "id": 330,
    "question": "138. 按照《武器装备科研生产单位保密资格评分标准》的规定，达不到重点项要求的，中止审查或者复查。（  ）"
  },
  {
    "id": 331,
    "question": "139. 按照《器装备科研生产单位保密资格评分标准》的规定，达不到基本项要求的，应当中止审查或者复查。（  ） 三、单项选择题(下列各题中只有一个正确答案，共37题)"
  },
  {
    "id": 332,
    "question": "1. 《武器装备科研生产单位保密资格标准》的作用是（  ）\nA. 武器装备科研生产单位保密资格审查认定的依据                B. 武器装备科研生产许可管理的依据\nC. 进行产品质量审查认证的依据                                D. 违反单位保密规定进行处罚的依据"
  },
  {
    "id": 333,
    "question": "2. 一级保密资格单位保密委员会主任应当由谁担任（  ）\nA. 行政副职              B. 单位负责人             C. 综合处处长                  D. 纪委书记"
  },
  {
    "id": 334,
    "question": "3. 二级保密资格单位保密委员会主任或者保密工作领导小组组长由谁担任（  ）\nA. 单位法定代表人或者主要负责人                           B. 单位负责人\nC. 单位分管科研生产任务的负责人                           D. 单位行政负责人"
  },
  {
    "id": 335,
    "question": "4. 三级保密资格单位保密委员会主任或者保密工作领导小组组长由谁担任（  ）\nA. 单位法定代表人或者主要负责人                          B. 单位负责人\nC. 单位分管科研生产任务的负责人                          D. 单位行政负责人"
  },
  {
    "id": 336,
    "question": "5. 保密工作机构设置不符合要求的，现场审查组应当如何处理（  ）\nA. 中止审查或者复查                                 B. 按照规定扣分\nC. 批评教育后继续审查                               D. 帮助单位找出原因"
  },
  {
    "id": 337,
    "question": "6. —级保密资格单位涉密人员1000人（含）以上的，专职工作人员配备人数是（  ）\nA. 不得少于2人       B. 不得少于3人        C. 不得少于4人              D. 根据单位情况配备"
  },
  {
    "id": 338,
    "question": "7. 确定国家秘密事项的密级依据是（  ）\nA. 国家秘密及其密级具体范围                       B. 按照型号产品重要程度确定\nC. 承办人根据经验自行确定                         D. 定密责任人确定"
  },
  {
    "id": 339,
    "question": "8. 涉密人员的涉密等级如何划分（  ）\nA. 绝密机密秘密            B. 核心重要一般           C. 重要一般内部            D. 特殊重点普通"
  },
  {
    "id": 340,
    "question": "9. 单位应当根据涉密人员的涉密等级给予何种形式的保密待遇（  ）\nA. 保密津贴             B. 保密工资              C. 保密补贴                  D. 保密职称"
  },
  {
    "id": 341,
    "question": "10. 核心涉密人员的脱密期为（  ）\nA. 2年                 B. 3年                  C. 按照工龄折算                    D. 5年"
  },
  {
    "id": 342,
    "question": "11. 张某被界定为重要涉密人员，2006年3月5日因故被单位解聘，他的脱密期最早于（  ）截止。\nA. 2006年9月5日       B. 2007年3月5日         C. 2008年3月5日             D. 2009年3月6日"
  },
  {
    "id": 343,
    "question": "12. —份机密级文件保密期限是10年，密级标识应标注为（  ）\nA. 机密10年           B. 机密★             C. 机密★10年              D. 机密10年★"
  },
  {
    "id": 344,
    "question": "13. 某文件密级标识为“绝密★30年”，保密期限不超过（  ）\nA. 30年               B. 20年                C. 长期                   D. 25年"
  },
  {
    "id": 345,
    "question": "14. 机密级国家秘密事项保密期限是（  ）\nA. 一般不超过10年          B. 一般不超过15年        C. 一般不超过30年         D. —般不超过20年"
  },
  {
    "id": 346,
    "question": "15. 传递绝密级国家秘密载体的途径是（  ）\nA. 只能通过机要交通传递                                    B. 只能通过机要通信传递\nC. 可以通过机要通信、机要交通或者派专人传递                D. 只能专人直接传递"
  },
  {
    "id": 347,
    "question": "16. 复制国家秘密载体或者摘录属于国家秘密的内容的保密管理要求是（  ）\nA. 按照原件的密级、保密期限和知悉范围管理                  B. 可以在收文本上重新登记、编号即可\nC. 可以视情况加盖复印章                                    D. 可以作解密处理"
  },
  {
    "id": 348,
    "question": "17. 复制绝密国家秘密文件、资料或者物品，批准机关或者单位是（  ）\nA. 原确定密级的机关（单位）或者其上级机关\nB. 原确定密级的机关（单位）的上级机关或者上级保密工作部门\nC. 本单位领导或者保密委员会\nD. 本单位保密工作机构"
  },
  {
    "id": 349,
    "question": "18. 秘密级国家秘密载体应当存放在（  ）中。\nA. 密码文件柜               B. 铁皮柜                C. 带锁书柜                 D一般木柜"
  },
  {
    "id": 350,
    "question": "19. 保密要害部门、部位的新建、改建、扩建工程项目、保密防护措施与工程项目建设应当做到（  ）\nA. 同计划、同设计、同建设、同验收                        B. 同计划、同部署、同检查、同总结\nC. 同预算、同设计、同施工、同总结                        D. 同设计、同安排、同建设、同检查"
  },
  {
    "id": 351,
    "question": "20. 涉密计算机中的涉密电子文档，都应当标明密级标识，下面正确的是（  ）\nA. 应当标注在电子文档的首页\nB. 应当标注在电子文档的首页左上角\nC. 可以建立一个标明密级标识的文件夹，将涉密电子文档都存放在涉密文件夹中，就不需要对每一个涉密电子文档逐个标明密级\nD. 标注在电子文挡的首页的密级标识应当采用三号仿宋字体"
  },
  {
    "id": 352,
    "question": "21. 符合国家保密要求的涉密计算机屏幕保护程序等待时间应当（  ）\nA. 不超过一分钟          B. 不超过三分钟            C. 不超过五分钟              D. 不超过十分钟"
  },
  {
    "id": 353,
    "question": "22. 机密级计算机，身份鉴别口令的更新周期为（  ）\nA. 3天                    B. 7天                    C. 15天                      D. 30天"
  },
  {
    "id": 354,
    "question": "23. 秘密级计算机，身份鉴别口令的更新周期为（  ）\nA. 3天                  B. 7天                  C. 30天                     D. 60天"
  },
  {
    "id": 355,
    "question": "24. 当需要将病毒库、系统补丁程序等导入涉密信息系统时，可以采取下列哪种方式（  ）\nA. 通过中间机刻录只读光盘\nB. 通过中间机拷贝普通U盘\nC. 通过中间机使用带有读写锁定开关的专用U盘，并且确保在涉密信息系统内使用时U盘处于只读状态\nD. 使用MP3播放器作为存储介质进行导入"
  },
  {
    "id": 356,
    "question": "25. 某单位新购置一批带有无线互联功能的笔记本电脑，准备作为涉密便携式计算机使用，下列做法正确的是（  ） A. 将便携式计算机确定涉密等级并粘贴密级标识后，作为涉密计算机使用\nB. 在操作系统的“设备管理器中”将无线网卡禁用\nC. 从便携式计算机的BIOS设置中关闭无线网卡功能\nD. 拆除具有无线互联功能的硬件模块"
  },
  {
    "id": 357,
    "question": "26. 根据工作需要，配备专供外出携带的涉密计算机和存储介质，对于每次归还的设备和介质应（  ）\nA. 进行保密技术检查                                        B. 删除涉密文件后，放入保密柜保存\nC. 转交给其他涉密人员，继续携带外出使用                     D. 及时销毁"
  },
  {
    "id": 358,
    "question": "27. 使用便携式计算机，下列做法错误的是（  ）\nA. 非涉密便携式计算机不得存储或者处理涉密信息\nB. 涉密便携式携带外出应当履行程序，带出前后应进行检查\nC. 非涉密便携式计算机可以短暂存储涉密信息，使用完毕后立即删除\nD. 涉密便携式计算机应物理拆除无线联网模块"
  },
  {
    "id": 359,
    "question": "28. 对处理国家秘密的办公自动化设备管理要求是（  ）\nA. 禁止接入国际互联网                            B. 可以接入公共信息网\nC. 可以接入内部非涉密信息系统                    D. 可以与普通电话线连接使用"
  },
  {
    "id": 360,
    "question": "29. 涉密场所通信设备的使用要求是（  ）\nA. 禁止使用无线通信设备                          B. 可以使用无绳电话\nC. 可以用手机连接互联网                          D. 可以使用具有无线互联功能的设备"
  },
  {
    "id": 361,
    "question": "30. 新闻宣传的保密管理要求是（  ）\nA. 涉及科研生产业绩的新闻宣传要实事求是                     B. 单位内部的新闻宣传不用经过保密审查\nC. 涉密人员在内部刊物发表涉及科研生产的文章不需审查         D. 不得涉及国家秘密"
  },
  {
    "id": 362,
    "question": "31. 不符合涉密会议管理要求的做法是（  ）\nA. 涉密会议应当在具备安全保密条件的场所召开\nB. 国家秘密载体发放、清退、保管和销毁应当指定人员负责，履行相关手续\nC. 会议使用的音像等技术设备应当符合保密要求\nD. 未经审批的便携式计算机可以带入会场"
  },
  {
    "id": 363,
    "question": "32. 负责组织协调外场试验的保密管理工作的单位是（  ）\nA. 参试单位          B. 上级主管部门          C. 试验任务牵头单位                D. 协管部门"
  },
  {
    "id": 364,
    "question": "33. 分包涉密项目，应当选择的单位是（  ）\nA. 具有相应保密资格的单位                        B. 具有相应科研生产能力的单位\nC. 具有经济实力的单位                            D. 具有高科技实力的单位"
  },
  {
    "id": 365,
    "question": "34. 单位发生泄密事件，应当及时口头或者书面形式向当地（  ）如实报告。\nA. 公安部门         B. 国家安全部门              C. 机要部门                D. 保密行政管理部门"
  },
  {
    "id": 366,
    "question": "35. 《标准》中要求，与协作配套单位签订合同时应当明确的有关事项是（  ）\nA. 项目密级、保密要求、保密责任                     B. 质量标准、保密条款、保密协议\nC. 交付日期、保密要求、保密责任                     D. 付款方式、项目密级、保密条款"
  },
  {
    "id": 367,
    "question": "36. 携带国家秘密载体参加涉外活动的正确做法是（  ）\nA. 经审批后采取保护措施，使国家秘密载体始终处于自己有效控制范围之内\nB. 经过领导批准携带外出的，不必采取保护措施\nC. 携带外出参加涉外活动后向单位领导报告\nD. 工作需要携带外出的可以不必经过审批，但事后要备案"
  },
  {
    "id": 368,
    "question": "37. 保密工作档案建立要求是（  ）\nA. 内容完整真实          B. 内容简明扼要           C. 内容应当是原件              D. 内容应都是复印件"
  },
  {
    "id": 369,
    "question": "1. 制定《武器装备科研生产单位保密资格认定办法》的目的是进一步规范和加强武器装备科研生产单位保密资格认定工作，确保国家秘密安全。 （  ）"
  },
  {
    "id": 370,
    "question": "2. 制定《武器装备科研生产单位保密资格认定办法》的直接目的在于确保国家秘密安全，维护承担武器装备科研生产任务的企业事业单位的合法利益，维护社会公平和公正。（  ）"
  },
  {
    "id": 371,
    "question": "3. 《武器装备科研生产单位保密资格认定办法》是依据《中华人民共和国保守国家秘密法》等法律法规制定的一项规范性文件，具有约束力，必须遵照执行。 （  ）"
  },
  {
    "id": 372,
    "question": "4. 《武器装备科研生产单位保密资格认定办法》适用于承担涉密武器装备科研生产任务企业事业单位的保密资格认定工作。 （  ）"
  },
  {
    "id": 373,
    "question": "5. 武器装备科研生产单位保密资格认定工作坚持积极预防、突出重点、严格标准、严格管理的原则。 （  ）"
  },
  {
    "id": 374,
    "question": "6. 武器装备科研生产单位保密资格认定工作坚持依法管理、严格标准、严格程序、公平公正的原则。 （  ）"
  },
  {
    "id": 375,
    "question": "7. 武器装备科研生产单位保密资格分为一级、二级、三级三个等级。 （  ）"
  },
  {
    "id": 376,
    "question": "8. 取得一级保密资格的单位，可以承担绝密级、机密级、秘密级的武器装备科研生产任务。 （  ）"
  },
  {
    "id": 377,
    "question": "9. 取得二级保密资格的单位，可以承担机密级、秘密级的武器装备科研生产任务。 （  ）"
  },
  {
    "id": 378,
    "question": "10. 取得三级保密资格的单位，可以承担秘密级的武器装备科研生产任务。 （  ）"
  },
  {
    "id": 379,
    "question": "11. 取得保密资格的单位都应当被列入《武器装备科研生产单位保密资格名录》。 （  ）"
  },
  {
    "id": 380,
    "question": "12. 二级保密资格申请单位应当由国家军工保密资格认定委员会进行现场审查。 （  ）"
  },
  {
    "id": 381,
    "question": "13. 国家军工保密资格认定委员会负责建立保密资格认定审查专家库，聘任和管理保密资格认定人员。（  ）"
  },
  {
    "id": 382,
    "question": "14. 省、自治区、直辖市军工保密资格认定委员会可根据辖区内申请一级保密资格单位要求，审查批准本地区一级保密资格单位。 （  ）"
  },
  {
    "id": 383,
    "question": "15. 省、自治区、直辖市军工保密资格认定委员会受国家军工保密资格认定委员会委托，可以审查部分一级保密资格申请单位，但无权审批一级保密资格单位。 （  ）"
  },
  {
    "id": 384,
    "question": "16. 省、自治区、直辖市军工保密资格认定委员会的组成人员由省、自治区、直辖市保密委员会审批，无须报国家军工保密资格认定委员会批准。 （  ）"
  },
  {
    "id": 385,
    "question": "17. 省、自治区、直辖市军工保密资格认定委员会在国家军工保密资格认定委员会指导下开展工作，其组成人员应当报国家军工保密资格认定委员会批准。 （  ）"
  },
  {
    "id": 386,
    "question": "18. 国家和省、自治区、直辖市军工保密资格认定委员会都应当设立办公室，负责国家和省、自治区、直辖市军工保密资格认定委员会日常工作。 （  ）"
  },
  {
    "id": 387,
    "question": "19. 申请保密资格的单位应当是在我国境内登记注册的企业、社团或者事业法人。 （  ）"
  },
  {
    "id": 388,
    "question": "20. 包括个人独资企业在内的非公有制企业，都可以申请保密资格。 （  ）"
  },
  {
    "id": 389,
    "question": "21. 涉密武器装备科研生产任务是指承担武器装备科研生产的项目或者产品涉密。 （  ）"
  },
  {
    "id": 390,
    "question": "22. 在我国境内没有登记注册的单位不能申请保密资格。（  ）"
  },
  {
    "id": 391,
    "question": "23. 在我国已经登记注册的企业法人和事业法人都能申请保密资格。（  ）"
  },
  {
    "id": 392,
    "question": "24. 凡是已雇佣外籍人员的单位都不能申请保密资格。（  ）"
  },
  {
    "id": 393,
    "question": "25. 凡是有外商（含港澳台）投资的单位都不能申请保密资格。 （  ）"
  },
  {
    "id": 394,
    "question": "26. 申请保密资格的单位，1年内未发生严重泄密事件才具备申请保密资格的基本条件。 （  ）"
  },
  {
    "id": 395,
    "question": "27. 某公司申请二级保密资格，但2008年10月26日发生过一起泄密事件，其所在地审查认定机构可在事发半年后受理该公司提交的保密资格申请。 （  ）"
  },
  {
    "id": 396,
    "question": "28. 某公司2008年10月5日发生过一起泄密事件，该公司只能到2009年10月5日以后才能申请保密资格。（√） 29. 申请保密资格单位，仅需提交《武器装备科研生产单位保密资格申请书》、单位工商营业执照的正本（原件)和财务审计报告。 （  ）"
  },
  {
    "id": 397,
    "question": "30. 申请保密资格单位提供的申请材料中，包括公司章程和股东协议。 （  ）"
  },
  {
    "id": 398,
    "question": "31. 申请保密资格单位提供的申请材料，必须包括单位的组织机构代码证书原件。 （  ）"
  },
  {
    "id": 399,
    "question": "32. 申请保密资格的单位提供的申请材料中应当包括军队资格审查申请受理点、军工集团公司、项目总承包单位或者法律法规规定的有关部门出具的保密资格认定等级建议表。 （  ）"
  },
  {
    "id": 400,
    "question": "33. 已取得保密资格的国有企业事业单位，重新申请原保密资格等级的，只需提供《武器装备科研生产单位保密资格申请书》、上一个年度财务验资报告，申请高于原保密资格等级的还需要提供密级证明。 （  ）"
  },
  {
    "id": 401,
    "question": "34. 不具有公司性质的单位免于提供单位章程。（  ）"
  },
  {
    "id": 402,
    "question": "35. 受理机构收到申请单位申请书及相关材料后，应当对申请材料的完备性以及是否符合申请条件进行审查。（√） 36. 受理机构应当在5个工作内对作出受理决定的单位申请材料进行书面审查。只有通过书面审查的单位，才可以进行现场审查。 （  ）"
  },
  {
    "id": 403,
    "question": "37. 受理机构收到申请单位《武器装备科研生产单位保密资格申请书》及相关材料后，应当在5个工作日内对申请材料的真实性进行书面审查。 （  ）"
  },
  {
    "id": 404,
    "question": "38. 凡是通过受理机构书面审查并决定受理的单位，都必须接受现场审查。 （  ）"
  },
  {
    "id": 405,
    "question": "39. 对通过书面审查的单位，保密行政管理部门应当会同共同审批部门，在25个工作日内组成现场审查组进行现场审查。（  ）"
  },
  {
    "id": 406,
    "question": "40. 现场审查组工作人员应当从保密资格认定审查专家库中抽取。 （  ）"
  },
  {
    "id": 407,
    "question": "41. 二级、三级保密资格申请单位现场审查组负责人由省、自治区、直辖市保密行政管理部门会同同级国防科技工业管理部门确定。 （  ）"
  },
  {
    "id": 408,
    "question": "42. 审查组工作人员人数应当为3—5人。 （  ）"
  },
  {
    "id": 409,
    "question": "43. 审查组工作人员人数应当为5—8人，包括2—3名保密技术检查人员。（  ）"
  },
  {
    "id": 410,
    "question": "44. 为了确保现场审查的真实性，审查组进行现场审查之前，不允许通知被审查单位。（  ）"
  },
  {
    "id": 411,
    "question": "45. 为了确保现场审查的正常进行，审查组应当在进行现场审查的前一天通知被审查单位。（  ）"
  },
  {
    "id": 412,
    "question": "46. 为了确保现场审查的正常进行，审查组应当提前5个工作日书面通知被审查单位。 （  ）"
  },
  {
    "id": 413,
    "question": "47. 根据现场审查程序要求，审查组应当首先进行实地现场审查，然后再听取被审查单位的汇报。（  ）"
  },
  {
    "id": 414,
    "question": "48. 审查组现场审查时，应当首先听取被审查单位情况汇报和对有关事项的说明。 （  ）"
  },
  {
    "id": 415,
    "question": "49. 审查组对被审查单位进行现场审查时应当完整、客观地进行记录。 （  ）"
  },
  {
    "id": 416,
    "question": "50. 审查组对被审查单位进行现场审查时，应当按照一定比例随机抽取部分涉密人员进行保密知识闭卷测试。（√） 51. 现场审查时，审查组应当对被审查单位的所有涉密人员进行保密知识测试。 （  ）"
  },
  {
    "id": 417,
    "question": "52. 审查组现场审查结束前，应当依据《武器装备科研生产单位保密资格评分标准》对被审查单位进行评议，形成审查意见和结论，以此作为该申请单位能否取得保密资格的最终依据。 （  ）"
  },
  {
    "id": 418,
    "question": "53. 在评议过程中对具体项目评分产生意见分歧时，可采取投票表决的方式，票数超过半数的意见，形成审查组意见；票数相当时，由审查组组长决定，形成审查意见。（  ）"
  },
  {
    "id": 419,
    "question": "54. 为了确保现场审查工作的公正性，审查组在最终作出审查结论以前，应当征求被审查单位的惠见。（  ）"
  },
  {
    "id": 420,
    "question": "55. 审查组对现场审查进行评议时，只能通过表决的方式，根据少数服从多数的原则形成最后的审查结论。（  ）"
  },
  {
    "id": 421,
    "question": "56. 审查组在对被审查单位现场审查情况进行评议吋，可以通过集体研究形成或者表决形成审查意见和结论。（√） 57. 申请或者取得保密资格的单位对有关行政决定有不服的，可以申请行政复议。 （  ）"
  },
  {
    "id": 422,
    "question": "58. 审查组应当向被审查单位通报审查意见和结论，对存在的问题提出整改要求。 （  ）"
  },
  {
    "id": 423,
    "question": "59. 被审查单位对审查意见和审查结论进行确认，由法定代表人或者主要负责人在《武器装备科研生产单位保密资格审查（复查）意见书》签署同意或者不同意的意见，并签名确认。 （  ）"
  },
  {
    "id": 424,
    "question": "60. 被审查单位对审查结论有异议的，可以要求审查组对有关事项进行复查，审查组可依据复查的结果修订已经作出的审查结论。 （  ）"
  },
  {
    "id": 425,
    "question": "61. 审查组向被审查单位通报审查意见和审查结论后，无论被审查单位是否签署意见，该审查结论对被审查单位都有效。 （  ）"
  },
  {
    "id": 426,
    "question": "62. 审查中发现被审查单位在基本项上达不到《武器装备科研生产单位保密资格标准》，应当中止审查，并要求其采取整改措施。 （  ）"
  },
  {
    "id": 427,
    "question": "63. 对中止审查的单位，3个月后视整改情况决定是否恢复审查。 （  ）"
  },
  {
    "id": 428,
    "question": "64. 被中止审查单位经过3个月整改后，审查组应当恢复审查。 （  ）"
  },
  {
    "id": 429,
    "question": "65. 省、自治区、直辖市军工保密资格认定委员会应当将审查同意的保密资格单位的有关材料，报国家军工保密资格认定委员会批准。 （  ）"
  },
  {
    "id": 430,
    "question": "66. 省、自治区、直辖市军工保密资格认定委员会应当将审查批准的保密资格申请单位有关材料，报军工保密资格认定委员会复核备案。 （  ）"
  },
  {
    "id": 431,
    "question": "67. 保密资格证书有效期为5年，保密资格有效期从行政机关审批通过之日起计算。有效期满，保密资格即行废止，自动注销。  （  ）"
  },
  {
    "id": 432,
    "question": "68. 某公司于2007年5月3日通过保密资格认定现场审查，该公司保密资格有效期从2007年5月3日计算。（×） 69. 某所于2008年2月7日通过一级保密资格现场审查，2008年3月21日国家军工保密认证委发布的《武器装备科研生产单位保密资格名录》中有该公司，则该公司取得保密资格的时间是2008年3月21日。 （  ）"
  },
  {
    "id": 433,
    "question": "70. 取得保密资格的单位应当对照《武器装备科研生产单位保密资格标准》实行年度自检制度，每年1月31日前，向作出审批决定的行政机关报送上一年度单位基本情况变化和保密资格标准落实情况自检报告。（  ）"
  },
  {
    "id": 434,
    "question": "71. 取得保密资格单位的年度自检报告，于每年第一季度向作出审批决定的行政机关报送。 （  ）"
  },
  {
    "id": 435,
    "question": "72. 对已经取得保密资格满2至3年的单位，国家或者省、自治区、直辖市军工保密资格认定委员会应当进行复查。 （  ）"
  },
  {
    "id": 436,
    "question": "73. 国家和省、自治区、直辖市军工保密资格认定委员会对已经取得保密资格单位进行复查时，如果发现被复查单位基本项达不到《武器装备科研生产单位保密资格标准》，应当中止复查，给予警告，并要求限期釆取整改措施。（√） 74. 对中止复查的单位，3个月后重新复查，复查仍未通过的，撤销其保密资格。 （  ）"
  },
  {
    "id": 437,
    "question": "75. 取得保密资格的单位出现法定代表人、单位名称或者注册地址变更的，应当申请证书信息变更。 （  ）"
  },
  {
    "id": 438,
    "question": "76. 取得保密资格的单位，因为法定代表人、注册地址或者单位名称发生变更的，应当重新申请。 （  ）"
  },
  {
    "id": 439,
    "question": "77. 申请变更保密资格证书的单位，应当向作出审批决定的行政机关报告，经审核同意后办理变更手续。（  ）"
  },
  {
    "id": 440,
    "question": "78. 取得保密资格的单位，如果需要提高保密资格等级或者资本构成、单位性质发生重大变化的，应当重新申请保密资格。（  ）"
  },
  {
    "id": 441,
    "question": "79. 取得保密资格的单位，如果需要提高保密资格等级或者资本、单位性质发生重大变化的，应当于发生相关情形后60个工作日内重新申请保密资格。 （  ）"
  },
  {
    "id": 442,
    "question": "80. 某高校已经取得二级保密资格。因为学校搬迁到新的校区，导致涉密场所发生重大变化。学校领导认为这只是工作地点调整，只要向有关军工保密认定委报告就可以，不需要重新申请保密资格。 （  ）"
  },
  {
    "id": 443,
    "question": "81. 就当注销保密资格的情形是：保密资格有效期满，不再申请的；单位申请注销的；法人依法终止的。（  ）"
  },
  {
    "id": 444,
    "question": "82. 国家、省、自治区、直辖市军工保密资格认定委员会应当自受理复议申请之日起60个工作日内作出最终决定。（  ）"
  },
  {
    "id": 445,
    "question": "83. 申请单位对审批决定有异议的，可以申请行政复议。（  ）"
  },
  {
    "id": 446,
    "question": "84. 取得保密资格的单位，将涉密武器装备科研生产任务分包给不具有保密资格的单位，国家军工保密资格认定委员会将责令其终止分包合同，并限期整改。 （  ）"
  },
  {
    "id": 447,
    "question": "85. 取得保密资格的单位，选择不具有保密资格的单位分包机密级武器装备科研生产任务的，撤销其保密资格。构成犯罪的，依法追究刑事责任。 （  ）"
  },
  {
    "id": 448,
    "question": "86. 取得保密资格的单位存在重大泄密隐患时，应当撤销该单位的保密资格。 （  ）"
  },
  {
    "id": 449,
    "question": "87. 审查人员违反《武器装备科研生产单位保密资格认定办法》，滥用职权、徇私舞弊、玩忽职守的，撤销其审查资格，依法依纪给予行政处分；构成犯罪的，依法追究刑事责任。 （  ）"
  },
  {
    "id": 450,
    "question": "1. 《武器装备科研生产单位保密资格标准》仅依据党和国家有关保密工作的方针政策制定。 （  ）"
  },
  {
    "id": 451,
    "question": "2. 按照《武器装备科研生产单位保密资格评分标准》的规定，达不到重点项目要求的，应当中止审查。（  ）"
  },
  {
    "id": 452,
    "question": "3. 按照《武器装备科研生产单位保密资格评分标准》的规定，达不到基本项要求的，应当加重扣分，扣分超出分项目分值的，以分项目分值扣分。 （  ）"
  },
  {
    "id": 453,
    "question": "4. 按照《武器装备科研生产单位保密资格评分标准》规定，保密工作机构设置不符合标准要求的，应当中止审查或者复查。 （  ）"
  },
  {
    "id": 454,
    "question": "5. 按照《武器装备科研生产单位保密资格评分标准》规定，分包涉密任务，选择的协作配套单位不具有相应保密资格的，应当加重扣分。 （  ）"
  },
  {
    "id": 455,
    "question": "1. 现场审查时，应当对发现的问题进行记录并对当事人进行确认。                 （  ）"
  },
  {
    "id": 456,
    "question": "2. 现场审查时，如果发现审批单记录内容与实际不一致，就可以直接扣分。               （  ）"
  },
  {
    "id": 457,
    "question": "3. 涉密信息系统通过测讯取得使用许可证后，对测评认可的项目可以不进行检查。            （  ）"
  },
  {
    "id": 458,
    "question": "4. 没有经过系统测评和保密行政管理部门审批的涉密信息系统、涉密信息设备和涉密存储设备只能试运行，在试运行期间不得存储和处理涉密信息。              （  ）"
  },
  {
    "id": 459,
    "question": "5. 将手机和传真机接入涉密信息系统、涉密信息设备和涉密存储设备，就是破坏物理隔离。          （  ）"
  },
  {
    "id": 460,
    "question": "6. 在涉及涉密信息系统、涉密信息设备和涉密存储设备中，为保护国家秘密的安全，可以采用各种加密措施对涉密信息进行保护。                  （  ）"
  },
  {
    "id": 461,
    "question": "7. 存储机密级信息的硬盘经格式化后，可以降密或者解密使用。                  （  ）"
  },
  {
    "id": 462,
    "question": "8. 办公自动化设备应当粘贴标签，标明密级和使用用途。（  ）"
  },
  {
    "id": 463,
    "question": "9. 违规外联监控系统应禁止系统内用户非授权的外部连接，并有技术手段对系统内的外部连接行为进行实时监控、实时报警和实时阻断。                （  ）"
  },
  {
    "id": 464,
    "question": "10. 某单位涉密计算机都是单机管理，一部门为了工作方便自行将部门内几台涉密计算机通过集线器连接，用于共享文件和打印共享。这种做法符合保密要求。           （  ）"
  },
  {
    "id": 465,
    "question": "11. 涉密便携式计算机一般不存储涉密信息，所以涉密便携式计算机丢失不须追究其泄密责任。         （  ）"
  },
  {
    "id": 466,
    "question": "12. 应禁止使用具有无线互联功能的信息设备处理涉密信息，凡用于处理涉密信息的信息设备应将具有无线联网功能的硬件模块拆除或者禁用。              （  ）"
  },
  {
    "id": 467,
    "question": "13. 采用接地良好的屏蔽电缆，并与其他并行非屏蔽电缆保持有效距离时，涉密信息的传输可以不使用密码保护的措施。  （  ）"
  },
  {
    "id": 468,
    "question": "14. 涉密信息系统、涉密信息设备和涉密存储设备中使用的信息设备必须采用电磁泄漏发射防护措施。       （×） 15. 处理涉密信息的便携式计算机不需要采取电磁泄漏发射防护措施。                （  ）"
  },
  {
    "id": 469,
    "question": "16. 加密传输是一种非常有效并经常使用的方法，也能解决输入和输出端的电磁信息泄漏问题。         （  ）"
  },
  {
    "id": 470,
    "question": "17. “红信号”是指那些一旦被窃取，会造成信息泄密的信号。其他的信号则称为“黑信号”。         （  ）"
  },
  {
    "id": 471,
    "question": "18. 最小警戒距离是指涉密信息设备安置点至单位保卫部门可有效控制的最近边界的距离。          （  ）"
  },
  {
    "id": 472,
    "question": "19. 计算机的辐射和传导泄漏发射可以通过空间辐射发射，通过金属线缆传导发射，但是不能通过暖气管、自来水管等管道发射。                  （  ）"
  },
  {
    "id": 473,
    "question": "20. 禁止使用具有打印、复印、传真等多功能一体机处理国家秘密信息。                （  ）"
  },
  {
    "id": 474,
    "question": "21. 涉密办公自动化设备的报废应当拆除涉密存储部件上交保密工作机构，将剩余部分做报废处理。       （√） 22. 涉密场所的无绳电话，只要不使用，就不会产生泄密隐患。                  （  ）"
  },
  {
    "id": 475,
    "question": "23. 利用涉密信息系统、涉密信息设备和涉密存储设备的网络环境开通的内部IP电话，只要不连接外部的电话网，就符合保密要求。                  （  ）"
  },
  {
    "id": 476,
    "question": "24. 涉密信息系统的安全威胁主要来自外部的恶意攻击和病毒入侵，所以一定要做好安全防护工作。       （×） 25. 重要涉密场所禁止使用手机和无绳电话。    （  ）"
  },
  {
    "id": 477,
    "question": "26. 禁止使用非涉密办公自动化设备存储和处理和存储涉密信息。                 （  ）"
  },
  {
    "id": 478,
    "question": "27. 办公自动化设备可以联入单位非涉密信息系统。  （  ）"
  },
  {
    "id": 479,
    "question": "28. 涉密会议应当在具备安全保密条件的场所召开，重要涉密会议应当在内部场所召开，重要涉密会议会前应制定保密工作方案，并向单位保密工作机构备案，必要时保密工作机构应当派人监督和检查。                  （√） 29. 按照《武器装备科研生产单位保密资格评分标准》规定，涉密信息系统未经国家保密行政管理部门审批就存储、处理涉密信息的，中止审查或者复查。            （  ）"
  },
  {
    "id": 480,
    "question": "30. 涉密信息系统、涉密信息设备和涉密存储设备连接国际互联网和其他公共信息网络的，中止审查或者复查。    （  ）"
  },
  {
    "id": 481,
    "question": "31. 涉密信息远程传输未按照国家有关部门要求采取密码保护措施的，加重扣分。            （  ）"
  },
  {
    "id": 482,
    "question": "32. 处理涉密信息的办公自动化设备连接国际互联网或者其他公共信息网络的，中止审查或者复查。       （√） 33. 使用连接国际互联网或者其他公共信息网络的办公自动化设备处理涉密信息的，中止审查或者复查。      （  ）"
  },
  {
    "id": 483,
    "question": "34. 涉密信息系统的涉密等级、安全域划分、应用系统名称和数量应当与使用许可证批准的一致。        （  ）"
  },
  {
    "id": 484,
    "question": "35. 涉密信息系统的使用许可证涉及事项发生变化时，应当按照有关规定及时报告。            （  ）"
  },
  {
    "id": 485,
    "question": "36. 单位应当提供涉密信息系统完整的拓扑结构图。  （  ）"
  },
  {
    "id": 486,
    "question": "37. 提供的涉密信息系统拓扑结构图至少应当注明每一个安全域的边界。               （  ）"
  },
  {
    "id": 487,
    "question": "38. 信息化管理部门应当是单位的内设部门。    （  ）"
  },
  {
    "id": 488,
    "question": "39. 信息化管理部门应当至少配备一名懂信息系统和信息设备的专业技术管理人员。            （  ）"
  },
  {
    "id": 489,
    "question": "40. 二级、三级保密资格单位的运行维护机构可以委托给具有运行维护能力的机构（单位）。          （  ）"
  },
  {
    "id": 490,
    "question": "41. 运行维护机构应当配置涉密计算机和信息系统的运行维护人员（简称“三员”）。           （  ）"
  },
  {
    "id": 491,
    "question": "42. “三员”应当由信息化管理部门正式任命。   （  ）"
  },
  {
    "id": 492,
    "question": "43. 风险评估报告应当上报信息安全管理部门、主管领导和保密部门审阅。               （  ）"
  },
  {
    "id": 493,
    "question": "44. 安全保密产品的策略，如果是出厂设置，未根据涉密计算机和信息系统的安全实际进行设置，则应当扣分。    （  ）"
  },
  {
    "id": 494,
    "question": "45. 对数据库服务器、磁盘阵列中集中存储的涉密信息，应当采取技术措施，实现安全可控。          （  ）"
  },
  {
    "id": 495,
    "question": "46. 涉密信息系统机房应当确定为保密要害部位，划定安全控制区域，采取符合有关规定和标准要求的安全控制措施。  （  ）"
  },
  {
    "id": 496,
    "question": "47. 涉密信息系统和涉密信息设备应当根据国家秘密的知悉范围，实现主体对客体的访问授权。        （  ）"
  },
  {
    "id": 497,
    "question": "48. 用于身份鉴别的物理装置应当按照国家秘密载体的要求进行管控。                （  ）"
  },
  {
    "id": 498,
    "question": "49. 涉密信息系统和涉密信息设备使用的各种软件应当统一管理。                 （  ）"
  },
  {
    "id": 499,
    "question": "50. 涉密信息设备维修中应当对外来维修人员履行审批程序并全程旁站陪同。              （  ）"
  },
  {
    "id": 500,
    "question": "51. 单位应当配备专供外出携带的涉密信息设备，并由专人集中管理。                （  ）"
  },
  {
    "id": 501,
    "question": "52. 涉密计算机等信息设备严禁使用非涉密移动存储介质。（  ）"
  }
]